{
  "date": "2026-06-15",
  "puzzle": {
    "verseRef": "17:1",
    "reference": "Surah Al-Isra (17:1)",
    "segments": [
      "Glorified",
      "is He who",
      "took His servant",
      "by night"
    ],
    "translations": [
      "Exalted (is) the One Who took His servant (by) night from",
      "Al-Masjid Al-Haraam Al-Masjid Al-Haraam to Al-Masjid Al-Aqsa Al-Masjid Al-Aqsa",
      "which We blessed its surroundings that We may show him of",
      "Our Signs Indeed He He (is) the All-Hearer the All-Seer"
    ],
    "hint": "This verse describes the Prophet Muhammad's miraculous nighttime journey from the Sacred Mosque to the Farthest Mosque.",
    "arabic": "سُبْحَـٰنَ ٱلَّذِىٓ أَسْرَىٰ بِعَبْدِهِۦ لَيْلًۭا مِّنَ ٱلْمَسْجِدِ ٱلْحَرَامِ إِلَى ٱلْمَسْجِدِ ٱلْأَقْصَا ٱلَّذِى بَـٰرَكْنَا حَوْلَهُۥ لِنُرِيَهُۥ مِنْ ءَايَـٰتِنَآ ۚ إِنَّهُۥ هُوَ ٱلسَّمِيعُ ٱلْبَصِيرُ",
    "words": [
      "سُبْحَـٰنَ ٱلَّذِىٓ أَسْرَىٰ بِعَبْدِهِۦ لَيْلًۭا مِّنَ",
      "ٱلْمَسْجِدِ ٱلْحَرَامِ إِلَى ٱلْمَسْجِدِ ٱلْأَقْصَا",
      "ٱلَّذِى بَـٰرَكْنَا حَوْلَهُۥ لِنُرِيَهُۥ مِنْ",
      "ءَايَـٰتِنَآ ۚ إِنَّهُۥ هُوَ ٱلسَّمِيعُ ٱلْبَصِيرُ"
    ],
    "verseEn": "Exalted is He who took His Servant [i.e., Prophet Muḥammad (ﷺ)] by night from al-Masjid al-Ḥarām to al-Masjid al-Aqṣā, whose surroundings We have blessed, to show him of Our signs. Indeed, He is the Hearing, the Seeing."
  },
  "generated": true,
  "model": "auto (chain)"
}