{
  "date": "2026-06-26",
  "puzzle": {
    "verseRef": "23:3",
    "reference": "Surah Al-Mu'minun (23:3)",
    "segments": [
      "خَلَقَ الْإِنسَانَ مِنْ نُطْفَةٍ",
      "فَجَعَلَهُ نُطْفَةً",
      "ثُمَّ خَلَقَ فَسَوَّىٰهُ",
      "فَجَعَلَ لَهُ سَمْعًا وَبَصَرًا",
      "وَقَدْ خَصَّ بِذَٰلِكَ قَلْبًا فَهَلْ مِن مُّدَّكِرِ"
    ],
    "translations": [
      "Those who",
      "[they]",
      "from",
      "the vain talk",
      "turn away"
    ],
    "hint": "An early Makkan revelation describing the stages of human creation from a drop until receiving hearing and sight",
    "arabic": "وَٱلَّذِينَ هُمْ عَنِ ٱللَّغْوِ مُعْرِضُونَ",
    "words": [
      "وَٱلَّذِينَ",
      "هُمْ",
      "عَنِ",
      "ٱللَّغْوِ",
      "مُعْرِضُونَ"
    ],
    "verseEn": "And they who turn away from ill speech"
  },
  "generated": true,
  "model": "auto (chain)"
}